{
 "imageLocks": {
  "wait-for-it-public": {
   "configs": {
    "amd64": "{\"config\": {\"accounts\":{\"groups\":[{\"gid\":65532,\"groupname\":\"nonroot\",\"members\":[]}],\"run-as\":\"65532\",\"users\":[{\"gid\":65532,\"homedir\":\"\",\"shell\":\"\",\"uid\":65532,\"username\":\"nonroot\"}]},\"annotations\":{\"dev.chainguard.image.title\":\"wait-for-it\",\"org.opencontainers.image.authors\":\"Chainguard Team https://www.chainguard.dev/\",\"org.opencontainers.image.source\":\"https://github.com/chainguard-images/images-private/tree/main/images/wait-for-it\",\"org.opencontainers.image.title\":\"wait-for-it\",\"org.opencontainers.image.url\":\"https://images.chainguard.dev/directory/image/wait-for-it/overview\",\"org.opencontainers.image.vendor\":\"Chainguard\"},\"archs\":[\"amd64\"],\"cmd\":\"\",\"contents\":{\"build_repositories\":[],\"keyring\":[],\"packages\":[\"bash=5.3-r12\",\"ca-certificates-bundle=20260413-r0\",\"coreutils=9.10-r5\",\"glibc-locale-posix=2.43-r6\",\"glibc=2.43-r6\",\"ld-linux=2.43-r6\",\"libacl1=2.3.2-r55\",\"libattr1=2.5.2-r56\",\"libcrypto3=3.6.2-r2\",\"libgcc=15.2.0-r11\",\"libpcre2-8-0=10.47-r0\",\"libselinux=3.10-r0\",\"libsepol=3.10-r2\",\"ncurses-terminfo-base=6.6.20260418-r0\",\"ncurses=6.6.20260418-r0\",\"wait-for-it=0.20200823-r9\",\"wolfi-baselayout=20230201-r29\"],\"repositories\":[\"https://apk.cgr.dev/chainguard\"],\"runtime_repositories\":[]},\"entrypoint\":{\"command\":\"/usr/bin/wait-for-it\",\"services\":{},\"shell-fragment\":\"\",\"type\":\"\"},\"environment\":{},\"include\":\"\",\"layering\":{\"budget\":10,\"strategy\":\"origin\"},\"paths\":[],\"stop-signal\":\"\",\"vcs-url\":\"\",\"volumes\":[],\"work-dir\":\"\"}}",
    "arm64": "{\"config\": {\"accounts\":{\"groups\":[{\"gid\":65532,\"groupname\":\"nonroot\",\"members\":[]}],\"run-as\":\"65532\",\"users\":[{\"gid\":65532,\"homedir\":\"\",\"shell\":\"\",\"uid\":65532,\"username\":\"nonroot\"}]},\"annotations\":{\"dev.chainguard.image.title\":\"wait-for-it\",\"org.opencontainers.image.authors\":\"Chainguard Team https://www.chainguard.dev/\",\"org.opencontainers.image.source\":\"https://github.com/chainguard-images/images-private/tree/main/images/wait-for-it\",\"org.opencontainers.image.title\":\"wait-for-it\",\"org.opencontainers.image.url\":\"https://images.chainguard.dev/directory/image/wait-for-it/overview\",\"org.opencontainers.image.vendor\":\"Chainguard\"},\"archs\":[\"arm64\"],\"cmd\":\"\",\"contents\":{\"build_repositories\":[],\"keyring\":[],\"packages\":[\"bash=5.3-r12\",\"ca-certificates-bundle=20260413-r0\",\"coreutils=9.10-r5\",\"glibc-locale-posix=2.43-r6\",\"glibc=2.43-r6\",\"ld-linux=2.43-r6\",\"libacl1=2.3.2-r55\",\"libattr1=2.5.2-r56\",\"libcrypto3=3.6.2-r2\",\"libgcc=15.2.0-r11\",\"libpcre2-8-0=10.47-r0\",\"libselinux=3.10-r0\",\"libsepol=3.10-r2\",\"ncurses-terminfo-base=6.6.20260418-r0\",\"ncurses=6.6.20260418-r0\",\"wait-for-it=0.20200823-r9\",\"wolfi-baselayout=20230201-r29\"],\"repositories\":[\"https://apk.cgr.dev/chainguard\"],\"runtime_repositories\":[]},\"entrypoint\":{\"command\":\"/usr/bin/wait-for-it\",\"services\":{},\"shell-fragment\":\"\",\"type\":\"\"},\"environment\":{},\"include\":\"\",\"layering\":{\"budget\":10,\"strategy\":\"origin\"},\"paths\":[],\"stop-signal\":\"\",\"vcs-url\":\"\",\"volumes\":[],\"work-dir\":\"\"}}",
    "index": "{\"config\": {\"accounts\":{\"groups\":[{\"gid\":65532,\"groupname\":\"nonroot\",\"members\":[]}],\"run-as\":\"65532\",\"users\":[{\"gid\":65532,\"homedir\":\"\",\"shell\":\"\",\"uid\":65532,\"username\":\"nonroot\"}]},\"annotations\":{\"dev.chainguard.image.title\":\"wait-for-it\",\"org.opencontainers.image.authors\":\"Chainguard Team https://www.chainguard.dev/\",\"org.opencontainers.image.source\":\"https://github.com/chainguard-images/images-private/tree/main/images/wait-for-it\",\"org.opencontainers.image.title\":\"wait-for-it\",\"org.opencontainers.image.url\":\"https://images.chainguard.dev/directory/image/wait-for-it/overview\",\"org.opencontainers.image.vendor\":\"Chainguard\"},\"archs\":[\"amd64\",\"arm64\"],\"cmd\":\"\",\"contents\":{\"build_repositories\":[],\"keyring\":[],\"packages\":[\"bash=5.3-r12\",\"ca-certificates-bundle=20260413-r0\",\"coreutils=9.10-r5\",\"glibc-locale-posix=2.43-r6\",\"glibc=2.43-r6\",\"ld-linux=2.43-r6\",\"libacl1=2.3.2-r55\",\"libattr1=2.5.2-r56\",\"libcrypto3=3.6.2-r2\",\"libgcc=15.2.0-r11\",\"libpcre2-8-0=10.47-r0\",\"libselinux=3.10-r0\",\"libsepol=3.10-r2\",\"ncurses-terminfo-base=6.6.20260418-r0\",\"ncurses=6.6.20260418-r0\",\"wait-for-it=0.20200823-r9\",\"wolfi-baselayout=20230201-r29\"],\"repositories\":[\"https://apk.cgr.dev/chainguard\"],\"runtime_repositories\":[]},\"entrypoint\":{\"command\":\"/usr/bin/wait-for-it\",\"services\":{},\"shell-fragment\":\"\",\"type\":\"\"},\"environment\":{},\"include\":\"\",\"layering\":{\"budget\":10,\"strategy\":\"origin\"},\"paths\":[],\"stop-signal\":\"\",\"vcs-url\":\"\",\"volumes\":[],\"work-dir\":\"\"}}"
   },
   "devConfigs": {},
   "eol": false,
   "latest": false,
   "main": "",
   "repo": "public/wait-for-it",
   "tags": [
    "latest"
   ]
  }
 },
 "repoTags": {
  "public/wait-for-it": {
   "wait-for-it-public": [
    "latest"
   ]
  }
 },
 "tests": {}
}
